MANIFEST.in
README.txt
redelv
setup.py
redelvlib/__init__.py
redelvlib/editgui.py
redelvlib/editors.py
redelvlib/generic_editors.py
redelvlib/graphics_editors.py
redelvlib/images.py
redelvlib/level_editors.py
redelvlib/patch_editor.py
redelvlib/record_editor.py
redelvlib/script_editor.py
redelvlib/sound_editors.py
redelvlib.egg-info/PKG-INFO
redelvlib.egg-info/SOURCES.txt
redelvlib.egg-info/dependency_links.txt
redelvlib.egg-info/requires.txt
redelvlib.egg-info/top_level.txt
redelvlib/resources/goatgoat.png
redelvlib/resources/icon.png
redelvlib/resources/inspect.png
redelvlib/resources/logo.png
redelvlib/resources/script.png
redelvlib/resources/sound.png