Metadata-Version: 1.1
Name: redelvlib
Version: 0.1.26
Summary: GUI editor using delv
Home-page: http://www.ferazelhosting.net/wiki/redelv
Author: Bryce Schroeder
Author-email: bryce.schroeder@gmail.com
License: GPL-3
Platform: UNKNOWN
Classifier: Development Status :: 2 - Pre-Alpha
Classifier: License :: OSI Approved :: GNU General Public License v3 or later (GPLv3+)
Classifier: Topic :: Games/Entertainment :: Role-Playing
